setup.py
digTokenizer/__init__.py
digTokenizer/rowTokenizer.py
digTokenizer/tokenizer.py
digTokenizer.egg-info/PKG-INFO
digTokenizer.egg-info/SOURCES.txt
digTokenizer.egg-info/dependency_links.txt
digTokenizer.egg-info/requires.txt
digTokenizer.egg-info/top_level.txt
digTokenizer/inputParser/CSVParser.py
digTokenizer/inputParser/InputParserFactory.py
digTokenizer/inputParser/JSONParser.py
digTokenizer/inputParser/__init__.py
digTokenizer/ngram/__init__.py
digTokenizer/ngram/ngram.py