Metadata-Version: 1.1
Name: digTokenizer
Version: 1.0.4
Summary: digTokenizer
Home-page: https://github.com/usc-isi-i2/dig-tokenizer
Author: Rajagopal Bojanapalli
Author-email: rajagopal067@gmail.com
License: UNKNOWN
Download-URL: https://github.com/usc-isi-i2/dig-tokenizer
Platform: UNKNOWN
